{
  "orgUnit": "<Your organization id>",
  "dataSetIdImam": "UTGrrHEFwtt",
  "reports": {
    "Integrated Management of Acute Malnutrition (IMAM) Program": {
      "dataValues": [
        {
          "categoryOptionCombo": "ye1QuAMRG5Z",
          "dataElement": "sJlRE8pCxD8",
          "row": 1,
          "column": 3
        },
        {
          "categoryOptionCombo": "ye1QuAMRG5Z",
          "dataElement": "GXJ2iH9UQaq",
          "row": 1,
          "column": 4
        },
        {
          "categoryOptionCombo": "ye1QuAMRG5Z",
          "dataElement": "ycIp2mBbTfu",
          "row": 1,
          "column": 5
        },
        {
          "categoryOptionCombo": "ye1QuAMRG5Z",
          "dataElement": "R8po0GOj34q",
          "row": 1,
          "column": 6
        },
        {
          "categoryOptionCombo": "ye1QuAMRG5Z",
          "dataElement": "ydW0M6PkpBt",
          "row": 1,
          "column": 7
        },
        {
          "categoryOptionCombo": "ye1QuAMRG5Z",
          "dataElement": "kj687W8jXg8",
          "row": 1,
          "column": 8
        },
        {
          "categoryOptionCombo": "ye1QuAMRG5Z",
          "dataElement": "vqA3rf2MjaZ",
          "row": 1,
          "column": 9
        },
        {
          "categoryOptionCombo": "ye1QuAMRG5Z",
          "dataElement": "PLaEGEei2kj",
          "row": 1,
          "column": 10
        },
        {
          "categoryOptionCombo": "ye1QuAMRG5Z",
          "dataElement": "Z62U9greQvZ",
          "row": 1,
          "column": 11
        },
        {
          "categoryOptionCombo": "ye1QuAMRG5Z",
          "dataElement": "QAgJq8StYNg",
          "row": 1,
          "column": 12
        },
        {
          "categoryOptionCombo": "ye1QuAMRG5Z",
          "dataElement": "uWDx72HqzPB",
          "row": 1,
          "column": 13,
          "getElementBack": true,
	  "fieldValue":"numberOfFemalesLessThanSix"
        },
        {
          "categoryOptionCombo": "PflKpozpO7b",
          "dataElement": "sJlRE8pCxD8",
          "row": 2,
          "column": 3
        },
        {
          "categoryOptionCombo": "PflKpozpO7b",
          "dataElement": "GXJ2iH9UQaq",
          "row": 2,
          "column": 4
        },
        {
          "categoryOptionCombo": "PflKpozpO7b",
          "dataElement": "ycIp2mBbTfu",
          "row": 2,
          "column": 5
        },
        {
          "categoryOptionCombo": "PflKpozpO7b",
          "dataElement": "R8po0GOj34q",
          "row": 2,
          "column": 6
        },
        {
          "categoryOptionCombo": "PflKpozpO7b",
          "dataElement": "ydW0M6PkpBt",
          "row": 2,
          "column": 7
        },
        {
          "categoryOptionCombo": "PflKpozpO7b",
          "dataElement": "kj687W8jXg8",
          "row": 2,
          "column": 8
        },
        {
          "categoryOptionCombo": "PflKpozpO7b",
          "dataElement": "vqA3rf2MjaZ",
          "row": 2,
          "column": 9
        },
        {
          "categoryOptionCombo": "PflKpozpO7b",
          "dataElement": "PLaEGEei2kj",
          "row": 2,
          "column": 10
        },
        {
          "categoryOptionCombo": "PflKpozpO7b",
          "dataElement": "Z62U9greQvZ",
          "row": 2,
          "column": 11
        },
        {
          "categoryOptionCombo": "PflKpozpO7b",
          "dataElement": "QAgJq8StYNg",
          "row": 2,
          "column": 12
        },
        {
          "categoryOptionCombo": "PflKpozpO7b",
          "dataElement": "uWDx72HqzPB",
          "row": 2,
          "column": 13,
          "getElementBack": true,
	  "fieldValue":"numberOfMaleLessThanSix"
        },
        {
          "categoryOptionCombo": "ye1QuAMRG5Z",
          "dataElement": "yIzJZ2BmFd6",
          "row": 4,
          "column": 3
        },
        {
          "categoryOptionCombo": "ye1QuAMRG5Z",
          "dataElement": "JqDGVQbcTtV",
          "row": 4,
          "column": 4
        },
        {
          "categoryOptionCombo": "ye1QuAMRG5Z",
          "dataElement": "JFx9b2mlFlf",
          "row": 4,
          "column": 5
        },
        {
          "categoryOptionCombo": "ye1QuAMRG5Z",
          "dataElement": "dPRbZQANfL8",
          "row": 4,
          "column": 6
        },
        {
          "categoryOptionCombo": "ye1QuAMRG5Z",
          "dataElement": "XClnCko5qQh",
          "row": 4,
          "column": 7
        },
        {
          "categoryOptionCombo": "ye1QuAMRG5Z",
          "dataElement": "JAG6AU2yvSy",
          "row": 4,
          "column": 8
        },
        {
          "categoryOptionCombo": "ye1QuAMRG5Z",
          "dataElement": "HJtrw2rMSOU",
          "row": 4,
          "column": 9
        },
        {
          "categoryOptionCombo": "ye1QuAMRG5Z",
          "dataElement": "dkctIyi9ymh",
          "row": 4,
          "column": 10
        },
        {
          "categoryOptionCombo": "ye1QuAMRG5Z",
          "dataElement": "CVFfiniCNC1",
          "row": 4,
          "column": 11
        },
        {
          "categoryOptionCombo": "ye1QuAMRG5Z",
          "dataElement": "cL7UQL05XZC",
          "row": 4,
          "column": 12
        },
        {
          "categoryOptionCombo": "ye1QuAMRG5Z",
          "dataElement": "NGP9fiylUVR",
          "row": 4,
          "column": 13,
          "getElementBack":true,
	  "fieldValue":"numberOfFemalesMoreThanSix"
        },
        {
          "categoryOptionCombo": "PflKpozpO7b",
          "dataElement": "yIzJZ2BmFd6",
          "row": 5,
          "column": 3
        },
        {
          "categoryOptionCombo": "PflKpozpO7b",
          "dataElement": "JqDGVQbcTtV",
          "row": 5,
          "column": 4
        },
        {
          "categoryOptionCombo": "PflKpozpO7b",
          "dataElement": "JFx9b2mlFlf",
          "row": 5,
          "column": 5
        },
        {
          "categoryOptionCombo": "PflKpozpO7b",
          "dataElement": "dPRbZQANfL8",
          "row": 5,
          "column": 6
        },
        {
          "categoryOptionCombo": "PflKpozpO7b",
          "dataElement": "XClnCko5qQh",
          "row": 5,
          "column": 7
        },
        {
          "categoryOptionCombo": "PflKpozpO7b",
          "dataElement": "JAG6AU2yvSy",
          "row": 5,
          "column": 8
        },
        {
          "categoryOptionCombo": "PflKpozpO7b",
          "dataElement": "HJtrw2rMSOU",
          "row": 5,
          "column": 9
        },
        {
          "categoryOptionCombo": "PflKpozpO7b",
          "dataElement": "dkctIyi9ymh",
          "row": 5,
          "column": 10
        },
        {
          "categoryOptionCombo": "PflKpozpO7b",
          "dataElement": "CVFfiniCNC1",
          "row": 5,
          "column": 11
        },
        {
          "categoryOptionCombo": "PflKpozpO7b",
          "dataElement": "cL7UQL05XZC",
          "row": 5,
          "column": 12
        },
        {
          "categoryOptionCombo": "PflKpozpO7b",
          "dataElement": "NGP9fiylUVR",
          "row": 5,
          "column": 13,
          "getElementBack":true,
	  "fieldValue":"numberOfMalesMoreThanSix"
        }
      ]
    },
    "Infant and Young Child Feeding": {
      "dataValues": [
        {
          "categoryOptionCombo": "kdsirVNKdhm",
          "dataElement": "pD6X0nQEiA5",
          "row": 1,
          "column": 2
        },
        {
          "categoryOptionCombo": "kdsirVNKdhm",
          "dataElement": "OvTOZ34zPpv",
          "row": 2,
          "column": 2
        }
      ]
    }
  }
}
